pycalcids/__init__.py
py_calci_ds-1.dist-info/LICENSE.txt
py_calci_ds-1.dist-info/METADATA
py_calci_ds-1.dist-info/WHEEL
py_calci_ds-1.dist-info/top_level.txt
py_calci_ds-1.dist-info/RECORD
